modul/__init__.py
modul/arif.py
lesson_arif-0.0.1.dist-info/METADATA
lesson_arif-0.0.1.dist-info/WHEEL
lesson_arif-0.0.1.dist-info/top_level.txt
lesson_arif-0.0.1.dist-info/RECORD
