Metadata-Version: 2.4
Name: lesson_arif
Version: 0.0.1
Summary: Lesson Arithmetic
Author: Mayor
Author-email: olimjonovzilxa@gmail.com
Requires-Python: >=3.6
Dynamic: author
Dynamic: author-email
Dynamic: description
Dynamic: description-content-type
Dynamic: requires-python
Dynamic: summary
